regraph/__init__.py
regraph/attribute_sets.py
regraph/audit.py
regraph/category_utils.py
regraph/command_parser.py
regraph/exceptions.py
regraph/graphs.py
regraph/hierarchies.py
regraph/primitives.py
regraph/rules.py
regraph/utils.py
regraph/backends/neo4j/__init__.py
regraph/backends/neo4j/graphs.py
regraph/backends/neo4j/hierarchies.py
regraph/backends/neo4j/old_hierarchy.py
regraph/backends/neo4j/cypher_utils/__init__.py
regraph/backends/neo4j/cypher_utils/categorical.py
regraph/backends/neo4j/cypher_utils/generic.py
regraph/backends/neo4j/cypher_utils/propagation.py
regraph/backends/neo4j/cypher_utils/query_analysis.py
regraph/backends/neo4j/cypher_utils/rewriting.py
regraph/backends/networkx/__init__.py
regraph/backends/networkx/graphs.py
regraph/backends/networkx/hierarchies.py
regraph/backends/networkx/plotting.py
regraph/neo4j/__init__.py
regraph/neo4j/graphs.py
regraph/neo4j/hierarchy.py
regraph/neo4j/cypher_utils/__init__.py
regraph/neo4j/cypher_utils/categorical.py
regraph/neo4j/cypher_utils/generic.py
regraph/neo4j/cypher_utils/propagation.py
regraph/neo4j/cypher_utils/query_analysis.py
regraph/neo4j/cypher_utils/rewriting.py
regraph/networkx/__init__.py
regraph/networkx/category_utils.py
regraph/networkx/hierarchy.py
regraph/networkx/plotting.py
regraph/networkx/rewriting_utils.py
regraph/networkx/type_checking.py
regraph-2.0.1.dist-info/LICENSE
regraph-2.0.1.dist-info/METADATA
regraph-2.0.1.dist-info/WHEEL
regraph-2.0.1.dist-info/top_level.txt
regraph-2.0.1.dist-info/RECORD
