Metadata-Version: 2.1
Name: regraph
Version: 2.0.1
Summary: Graph rewriting and graph-based knowledge representation framework
Home-page: http://dev.executableknowledge.org/ReGraph/
Author: Eugenia Oshurko
Author-email: yarutoua@gmail.com
License: MIT License
Platform: UNKNOWN
Classifier: Programming Language :: Python :: 3
Classifier: License :: OSI Approved :: MIT License
Classifier: Operating System :: OS Independent
Requires-Python: >=3.6
Requires-Dist: matplotlib
Requires-Dist: networkx
Requires-Dist: numpy
Requires-Dist: pyparsing
Requires-Dist: lrparsing
Requires-Dist: sympy
Requires-Dist: greenery
Requires-Dist: neo4j-driver
